{
  "format_version": "1.10.0",
  "animations": {
    "animation.block.wield": {
      "loop": true,
      "bones": {
        "rightitem": {
          "position": [ "c.is_first_person ? -4.0 : -1.0", "c.is_first_person ? -4.0 : -2.5", "c.is_first_person ? -2.0 : -11.0" ],
          "rotation": [ "c.is_first_person ? -25.0 : -11.0", "c.is_first_person ? 65.0 : 0.8", "c.is_first_person ? -50.0 : -7.5" ],
          "scale": [ "c.is_first_person ? 1.0 : 0.8375", "c.is_first_person ? 1.0 : 0.8375", "c.is_first_person ? 1.0 : 0.8375" ]
        }
      }
    }
  }
}