{
  "format_version": "1.20.80",
  "minecraft:recipe_shaped": {
    "description": {
      "identifier": "nicothekid:craft_x_mossy_stone_brick_slab_x_seagrass"
    },
    "priority": 4,
    "tags": [ "crafting_table" ],
    "pattern": [
      "DS",
      "S "
    ],
    "key": {
      "D": {
        "item": "minecraft:stone_brick_slab"
      },
      "S": {
        "item": "minecraft:seagrass"
      }
    },
    "result": {
      "item": "minecraft:mossy_stone_brick_slab",
      "count": 1
    },
    "unlock": [
      {
        "item": "minecraft:stone_brick_slab"
      },
      {
        "item": "minecraft:seagrass"
      }
    ]
  }
}
